gbdc.cpython-312-x86_64-linux-gnu.so
gbdc.libs/libacl-bf796b03.so.1.1.2253
gbdc.libs/libarchive-cdcae9ac.so.13.3.3
gbdc.libs/libattr-086f1aa3.so.1.1.2448
gbdc.libs/libbz2-a1e77c99.so.1.0.6
gbdc.libs/libcrypto-bdaed0ea.so.1.1.1k
gbdc.libs/liblz4-a5753129.so.1.8.3
gbdc.libs/liblzma-51a76f52.so.5.2.4
gbdc.libs/libxml2-54d19b2f.so.2.9.7
gbdc.libs/libzstd-76b78bac.so.1.4.4
gbdc-0.3.3.dist-info/METADATA
gbdc-0.3.3.dist-info/WHEEL
gbdc-0.3.3.dist-info/RECORD
gbdc-0.3.3.dist-info/licenses/LICENSE
