Metadata-Version: 2.2
Name: gbdc
Version: 0.3.3
Summary: Extension Module for GBD
Author-Email: Ashlin Iser <iser@kit.edu>, Christoph Jabs <christoph.jabs@helsinki.fi>
Maintainer-Email: Ashlin Iser <iser@kit.edu>
Classifier: License :: OSI Approved :: MIT License
Classifier: Programming Language :: C++
Project-URL: Homepage, https://benchmark-database.de
Project-URL: Documentation, https://udopia.github.io/gbdc/
Project-URL: Repository, https://github.com/Udopia/gbdc
